{
    "date_of_issue": "21.08.2024",
    "booking_number": "955-H1-0177310-2108",
    "agent_ID": "Olesia Berezhanska",
    "passenger_title": "",
    "passenger_name": "ALINA",
    "passenger_surname": "KARPENKO",
    "route": "KYIV-PASAZHYRSKYI - CHELM",
    "baggage": "3384.83GRN",
    "seat": "055 Повний",
    "flight_number": "",
    "departure_date": "09.09.2024 19:57",
    "arrival_date": "10.09.2024 05:42",
    "grand_total": "UAH 1500",
    "booking_date": "21.08.2024",
    "ticketing_date": "21.08.2024",
    "type_of_issue": "Ticket"
}